[
  {
    "id": "1",
    "name": "Mia J.",
    "mobile": "0349465559",
    "email": "Mia_J.@tech.com"
  },
  {
    "id": "2",
    "name": "Jack O.",
    "mobile": "0355746867",
    "email": "Jack_O.@tech.com"
  },
  {
    "id": "3",
    "name": "Violet M.",
    "mobile": "0340474318",
    "email": "Violet_M.@tech.com"
  },
  {
    "id": "4",
    "name": "Isabella A.",
    "mobile": "0313669002",
    "email": "Isabella_A.@tech.com"
  },
  {
    "id": "5",
    "name": "Jack A.",
    "mobile": "0338446147",
    "email": "Jack_A.@tech.com"
  },
  {
    "id": "6",
    "name": "Charlotte O.",
    "mobile": "0355554996",
    "email": "Charlotte_O.@tech.com"
  },
  {
    "id": "7",
    "name": "Thomas T.",
    "mobile": "0338124407",
    "email": "Thomas_T.@tech.com"
  },
  {
    "id": "8",
    "name": "Theodore C.",
    "mobile": "0316508350",
    "email": "Theodore_C.@tech.com"
  },
  {
    "id": "9",
    "name": "Olivia O.",
    "mobile": "0322465818",
    "email": "Olivia_O.@tech.com"
  },
  {
    "id": "10",
    "name": "Arthur I.",
    "mobile": "0313129840",
    "email": "Arthur_I.@tech.com"
  },
  {
    "id": "11",
    "name": "Arthur O.",
    "mobile": "039486749",
    "email": "Arthur_O.@tech.com"
  },
  {
    "id": "12",
    "name": "Jasper J.",
    "mobile": "0354209066",
    "email": "Jasper_J.@tech.com"
  },
  {
    "id": "13",
    "name": "Jasper J.",
    "mobile": "0336316875",
    "email": "Jasper_J.@tech.com"
  },
  {
    "id": "14",
    "name": "Mia A.",
    "mobile": "0351489138",
    "email": "Mia_A.@tech.com"
  },
  {
    "id": "15",
    "name": "Thomas I.",
    "mobile": "0328609844",
    "email": "Thomas_I.@tech.com"
  },
  {
    "id": "16",
    "name": "Violet V.",
    "mobile": "0342113824",
    "email": "Violet_V.@tech.com"
  },
  {
    "id": "17",
    "name": "Theodore T.",
    "mobile": "0344121829",
    "email": "Theodore_T.@tech.com"
  },
  {
    "id": "18",
    "name": "Charlotte L.",
    "mobile": "0317031160",
    "email": "Charlotte_L.@tech.com"
  },
  {
    "id": "19",
    "name": "Jasper C.",
    "mobile": "0324209444",
    "email": "Jasper_C.@tech.com"
  },
  {
    "id": "20",
    "name": "Levi M.",
    "mobile": "0313203836",
    "email": "Levi_M.@tech.com"
  },
  {
    "id": "21",
    "name": "Theodore A.",
    "mobile": "0342012055",
    "email": "Theodore_A.@tech.com"
  },
  {
    "id": "22",
    "name": "Elizabeth O.",
    "mobile": "0353648326",
    "email": "Elizabeth_O.@tech.com"
  },
  {
    "id": "23",
    "name": "Charlotte A.",
    "mobile": "0336165396",
    "email": "Charlotte_A.@tech.com"
  },
  {
    "id": "24",
    "name": "Elizabeth T.",
    "mobile": "0339899503",
    "email": "Elizabeth_T.@tech.com"
  },
  {
    "id": "25",
    "name": "Jasper I.",
    "mobile": "0355927585",
    "email": "Jasper_I.@tech.com"
  },
  {
    "id": "26",
    "name": "Asher A.",
    "mobile": "0321378679",
    "email": "Asher_A.@tech.com"
  },
  {
    "id": "27",
    "name": "Elizabeth T.",
    "mobile": "032962626",
    "email": "Elizabeth_T.@tech.com"
  },
  {
    "id": "28",
    "name": "Arthur A.",
    "mobile": "0332306982",
    "email": "Arthur_A.@tech.com"
  },
  {
    "id": "29",
    "name": "Theodore C.",
    "mobile": "0336291675",
    "email": "Theodore_C.@tech.com"
  },
  {
    "id": "30",
    "name": "Jasper A.",
    "mobile": "036523657",
    "email": "Jasper_A.@tech.com"
  },
  {
    "id": "31",
    "name": "Violet O.",
    "mobile": "0355811088",
    "email": "Violet_O.@tech.com"
  },
  {
    "id": "32",
    "name": "Jack A.",
    "mobile": "0337340723",
    "email": "Jack_A.@tech.com"
  },
  {
    "id": "33",
    "name": "Jasper J.",
    "mobile": "0313954191",
    "email": "Jasper_J.@tech.com"
  },
  {
    "id": "34",
    "name": "Cora T.",
    "mobile": "034810798",
    "email": "Cora_T.@tech.com"
  },
  {
    "id": "35",
    "name": "Cora C.",
    "mobile": "0323427990",
    "email": "Cora_C.@tech.com"
  },
  {
    "id": "36",
    "name": "Mia V.",
    "mobile": "0350811050",
    "email": "Mia_V.@tech.com"
  },
  {
    "id": "37",
    "name": "Elizabeth A.",
    "mobile": "037542862",
    "email": "Elizabeth_A.@tech.com"
  },
  {
    "id": "38",
    "name": "Arthur C.",
    "mobile": "0314465713",
    "email": "Arthur_C.@tech.com"
  },
  {
    "id": "39",
    "name": "Maia I.",
    "mobile": "0319256795",
    "email": "Maia_I.@tech.com"
  },
  {
    "id": "40",
    "name": "Arthur V.",
    "mobile": "0353892040",
    "email": "Arthur_V.@tech.com"
  },
  {
    "id": "41",
    "name": "Amelia O.",
    "mobile": "0322130390",
    "email": "Amelia_O.@tech.com"
  },
  {
    "id": "42",
    "name": "Asher L.",
    "mobile": "03946699",
    "email": "Asher_L.@tech.com"
  },
  {
    "id": "43",
    "name": "Amelia A.",
    "mobile": "032366588",
    "email": "Amelia_A.@tech.com"
  },
  {
    "id": "44",
    "name": "Oliver I.",
    "mobile": "0328803878",
    "email": "Oliver_I.@tech.com"
  },
  {
    "id": "45",
    "name": "Cora A.",
    "mobile": "0324534642",
    "email": "Cora_A.@tech.com"
  },
  {
    "id": "46",
    "name": "Theodore J.",
    "mobile": "0346108896",
    "email": "Theodore_J.@tech.com"
  },
  {
    "id": "47",
    "name": "Isabella I.",
    "mobile": "0353251217",
    "email": "Isabella_I.@tech.com"
  },
  {
    "id": "48",
    "name": "Olivia A.",
    "mobile": "0330956590",
    "email": "Olivia_A.@tech.com"
  },
  {
    "id": "49",
    "name": "Cora I.",
    "mobile": "0326846500",
    "email": "Cora_I.@tech.com"
  },
  {
    "id": "50",
    "name": "Theodore O.",
    "mobile": "0336669089",
    "email": "Theodore_O.@tech.com"
  },
  {
    "id": "51",
    "name": "Cora I.",
    "mobile": "0313966986",
    "email": "Cora_I.@tech.com"
  },
  {
    "id": "52",
    "name": "Isla M.",
    "mobile": "0314944590",
    "email": "Isla_M.@tech.com"
  },
  {
    "id": "53",
    "name": "Mia J.",
    "mobile": "0319310500",
    "email": "Mia_J.@tech.com"
  },
  {
    "id": "54",
    "name": "Arthur A.",
    "mobile": "0325884810",
    "email": "Arthur_A.@tech.com"
  },
  {
    "id": "55",
    "name": "Isla O.",
    "mobile": "0342711948",
    "email": "Isla_O.@tech.com"
  },
  {
    "id": "56",
    "name": "Jasper M.",
    "mobile": "0310543347",
    "email": "Jasper_M.@tech.com"
  },
  {
    "id": "57",
    "name": "Jack A.",
    "mobile": "0354355910",
    "email": "Jack_A.@tech.com"
  },
  {
    "id": "58",
    "name": "Elizabeth A.",
    "mobile": "0341877033",
    "email": "Elizabeth_A.@tech.com"
  },
  {
    "id": "59",
    "name": "Isabella J.",
    "mobile": "039400919",
    "email": "Isabella_J.@tech.com"
  },
  {
    "id": "60",
    "name": "Olivia V.",
    "mobile": "0310399636",
    "email": "Olivia_V.@tech.com"
  },
  {
    "id": "61",
    "name": "Oliver V.",
    "mobile": "0315856939",
    "email": "Oliver_V.@tech.com"
  },
  {
    "id": "62",
    "name": "Charlotte A.",
    "mobile": "0319254598",
    "email": "Charlotte_A.@tech.com"
  },
  {
    "id": "63",
    "name": "Charlotte A.",
    "mobile": "0340141411",
    "email": "Charlotte_A.@tech.com"
  },
  {
    "id": "64",
    "name": "Mia M.",
    "mobile": "0317507272",
    "email": "Mia_M.@tech.com"
  },
  {
    "id": "65",
    "name": "Jack A.",
    "mobile": "0354165073",
    "email": "Jack_A.@tech.com"
  },
  {
    "id": "66",
    "name": "Cora C.",
    "mobile": "0351914395",
    "email": "Cora_C.@tech.com"
  },
  {
    "id": "67",
    "name": "Levi M.",
    "mobile": "0329208011",
    "email": "Levi_M.@tech.com"
  },
  {
    "id": "68",
    "name": "Cora I.",
    "mobile": "0311516048",
    "email": "Cora_I.@tech.com"
  },
  {
    "id": "69",
    "name": "Arthur O.",
    "mobile": "0328348807",
    "email": "Arthur_O.@tech.com"
  },
  {
    "id": "70",
    "name": "Amelia O.",
    "mobile": "0322280294",
    "email": "Amelia_O.@tech.com"
  },
  {
    "id": "71",
    "name": "Cora C.",
    "mobile": "0356442696",
    "email": "Cora_C.@tech.com"
  },
  {
    "id": "72",
    "name": "Isabella J.",
    "mobile": "0333890472",
    "email": "Isabella_J.@tech.com"
  },
  {
    "id": "73",
    "name": "Charlotte A.",
    "mobile": "0322630416",
    "email": "Charlotte_A.@tech.com"
  },
  {
    "id": "74",
    "name": "Isla A.",
    "mobile": "0332203246",
    "email": "Isla_A.@tech.com"
  },
  {
    "id": "75",
    "name": "Olivia C.",
    "mobile": "0337952183",
    "email": "Olivia_C.@tech.com"
  },
  {
    "id": "76",
    "name": "Charlotte I.",
    "mobile": "0331327913",
    "email": "Charlotte_I.@tech.com"
  },
  {
    "id": "77",
    "name": "Isla C.",
    "mobile": "0331792039",
    "email": "Isla_C.@tech.com"
  },
  {
    "id": "78",
    "name": "Amelia C.",
    "mobile": "0329055360",
    "email": "Amelia_C.@tech.com"
  },
  {
    "id": "79",
    "name": "Elizabeth I.",
    "mobile": "0344807783",
    "email": "Elizabeth_I.@tech.com"
  },
  {
    "id": "80",
    "name": "Jasper J.",
    "mobile": "0350157916",
    "email": "Jasper_J.@tech.com"
  },
  {
    "id": "81",
    "name": "Arthur V.",
    "mobile": "0313522708",
    "email": "Arthur_V.@tech.com"
  },
  {
    "id": "82",
    "name": "Violet I.",
    "mobile": "0318821545",
    "email": "Violet_I.@tech.com"
  },
  {
    "id": "83",
    "name": "Theodore J.",
    "mobile": "0323181352",
    "email": "Theodore_J.@tech.com"
  },
  {
    "id": "84",
    "name": "Atticus C.",
    "mobile": "037201162",
    "email": "Atticus_C.@tech.com"
  },
  {
    "id": "85",
    "name": "Charlotte C.",
    "mobile": "034346273",
    "email": "Charlotte_C.@tech.com"
  },
  {
    "id": "86",
    "name": "Mia C.",
    "mobile": "0344885143",
    "email": "Mia_C.@tech.com"
  },
  {
    "id": "87",
    "name": "Maia O.",
    "mobile": "0314797977",
    "email": "Maia_O.@tech.com"
  },
  {
    "id": "88",
    "name": "Maia I.",
    "mobile": "0339037825",
    "email": "Maia_I.@tech.com"
  },
  {
    "id": "89",
    "name": "Charlotte O.",
    "mobile": "0317504554",
    "email": "Charlotte_O.@tech.com"
  },
  {
    "id": "90",
    "name": "Amelia O.",
    "mobile": "037794943",
    "email": "Amelia_O.@tech.com"
  },
  {
    "id": "91",
    "name": "Jasper A.",
    "mobile": "0327968506",
    "email": "Jasper_A.@tech.com"
  },
  {
    "id": "92",
    "name": "Amelia A.",
    "mobile": "0326094347",
    "email": "Amelia_A.@tech.com"
  },
  {
    "id": "93",
    "name": "Mia A.",
    "mobile": "0316868246",
    "email": "Mia_A.@tech.com"
  },
  {
    "id": "94",
    "name": "Mia T.",
    "mobile": "0324240415",
    "email": "Mia_T.@tech.com"
  },
  {
    "id": "95",
    "name": "Arthur A.",
    "mobile": "037235923",
    "email": "Arthur_A.@tech.com"
  },
  {
    "id": "96",
    "name": "Isabella A.",
    "mobile": "0345404873",
    "email": "Isabella_A.@tech.com"
  },
  {
    "id": "97",
    "name": "Violet A.",
    "mobile": "0349696353",
    "email": "Violet_A.@tech.com"
  },
  {
    "id": "98",
    "name": "Elizabeth I.",
    "mobile": "0349179881",
    "email": "Elizabeth_I.@tech.com"
  },
  {
    "id": "99",
    "name": "Olivia J.",
    "mobile": "034354695",
    "email": "Olivia_J.@tech.com"
  },
  {
    "id": "100",
    "name": "Asher T.",
    "mobile": "0341407662",
    "email": "Asher_T.@tech.com"
  }
]
